batchlink-1.1.0.dist-info/METADATA
batchlink-1.1.0.dist-info/WHEEL
batchlink-1.1.0.dist-info/entry_points.txt
batchlink-1.1.0.dist-info/licenses/LICENSE
batchlink/__init__.py
batchlink/__main__.py
batchlink/cli.py
batchlink/core.py
batchlink-1.1.0.dist-info/RECORD
