Metadata-Version: 2.1
Name: batchlink
Version: 1.1.0
Summary: Batch link files without modifying original files.
Keywords: batch-link,batch-rename,auto-rename
Author-Email: Jax Young <jaxvanyang@gmail.com>
License: MIT
Classifier: Programming Language :: Python :: 3 :: Only
Classifier: License :: OSI Approved :: MIT License
Classifier: Operating System :: POSIX
Classifier: Development Status :: 5 - Production/Stable
Classifier: Intended Audience :: End Users/Desktop
Classifier: Operating System :: OS Independent
Classifier: Topic :: Utilities
Project-URL: Source, https://github.com/jaxvanyang/batchlink
Project-URL: Repository, https://github.com/jaxvanyang/batchlink.git
Project-URL: Issues, https://github.com/jaxvanyang/batchlink/issues
Requires-Python: >=3.10
